[
  {
    "correct_answer": "Origami is an ancient Japanese art of paper folding.",
    "retrieved_context": "origami mathematics of is In conclusion field. origami involves transformation of sheet of paper. origami involves transformation of sheet of paper into intricate structures. origami involves application of principles. origami involves transformation into structures. origami involves transformation of sheet. origami involves transformation of sheet of paper into intricate three dimensional structures. origami involves transformation of flat sheet into intricate structures. origami involves transformation into intricate structures. origami mathematics of is fascinating field. origami involves transformation of flat sheet of paper into three dimensional structures. origami involves transformation. origami involves transformation of flat sheet of paper into intricate structures. origami involves transformation of flat sheet of paper. origami mathematics of is In conclusion fascinating field. origami involves application In geometry. origami involves transformation At its core. origami involves transformation of flat sheet into intricate three dimensional structures. origami involves transformation of flat sheet into structures. origami involves transformation of sheet of paper into structures. origami involves transformation into three dimensional structures. origami involves transformation of sheet of paper into three dimensional structures. origami involves transformation of sheet into structures. origami involves transformation into intricate three dimensional structures. origami involves transformation of sheet into intricate three dimensional structures. origami mathematics of is field. origami involves transformation of flat sheet of paper into intricate three dimensional structures. origami also involves application of mathematical principles. origami involves transformation of sheet into three dimensional structures. origami involves application. origami involves transformation of flat sheet into three dimensional structures. origami involves transformation of sheet into intricate structures. fascinating field is In conclusion. origami involves transformation of flat sheet of paper into structures. origami involves transformation of flat sheet. Origami art of paper folding. origami artists can create appealing models. origami artists maintaining integrity. origami artists can create visually appealing models. origami artists can create models By symmetrical folds. origami artists maintaining integrity of structure. origami artists can create models By incorporating folds. origami artists maintaining integrity of original structure. origami artists can create models By incorporating symmetrical folds. origami artists can create models. origami artists can create models By folds. origami artists can scale their designs. origami models explore possibilities in field. origami models explore new possibilities. origami models explore new possibilities in field. origami models explore possibilities. new possibilities is in field of robotics. origami models explore possibilities in field of robotics. origami models explore new possibilities in field of robotics. advanced origami models explore new possibilities in field. advanced origami models explore possibilities in field. advanced origami models explore possibilities in field of robotics. new possibilities is in field of robotics. advanced origami models explore possibilities. advanced origami models explore new possibilities. advanced origami models explore new possibilities in field of robotics.",
    "evaluation": 0
  },
  {
    "correct_answer": "Origami involves complex mathematical principles and theories.",
    "retrieved_context": "origami models explore possibilities in field. origami models explore new possibilities. origami models explore new possibilities in field. origami models explore possibilities. new possibilities is in field of robotics. origami models explore possibilities in field of robotics. origami models explore new possibilities in field of robotics. advanced origami models explore new possibilities in field. advanced origami models explore possibilities in field. advanced origami models explore possibilities in field of robotics. new possibilities is in field of robotics. advanced origami models explore possibilities. advanced origami models explore new possibilities. advanced origami models explore new possibilities in field of robotics. origami mathematics of is In conclusion field. origami involves transformation of sheet of paper. origami involves transformation of sheet of paper into intricate structures. origami involves application of principles. origami involves transformation into structures. origami involves transformation of sheet. origami involves transformation of sheet of paper into intricate three dimensional structures. origami involves transformation of flat sheet into intricate structures. origami involves transformation into intricate structures. origami mathematics of is fascinating field. origami involves transformation of flat sheet of paper into three dimensional structures. origami involves transformation. origami involves transformation of flat sheet of paper into intricate structures. origami involves transformation of flat sheet of paper. origami mathematics of is In conclusion fascinating field. origami involves application In geometry. origami involves transformation At its core. origami involves transformation of flat sheet into intricate three dimensional structures. origami involves transformation of flat sheet into structures. origami involves transformation of sheet of paper into structures. origami involves transformation into three dimensional structures. origami involves transformation of sheet of paper into three dimensional structures. origami involves transformation of sheet into structures. origami involves transformation into intricate three dimensional structures. origami involves transformation of sheet into intricate three dimensional structures. origami mathematics of is field. origami involves transformation of flat sheet of paper into intricate three dimensional structures. origami also involves application of mathematical principles. origami involves transformation of sheet into three dimensional structures. origami involves application. origami involves transformation of flat sheet into three dimensional structures. origami involves transformation of sheet into intricate structures. fascinating field is In conclusion. origami involves transformation of flat sheet of paper into structures. origami involves transformation of flat sheet. Origami art of paper folding. origami artists can create appealing models. origami artists maintaining integrity. origami artists can create visually appealing models. origami artists can create models By symmetrical folds. origami artists maintaining integrity of structure. origami artists can create models By incorporating folds. origami artists maintaining integrity of original structure. origami artists can create models By incorporating symmetrical folds. origami artists can create models. origami artists can create models By folds. origami artists can scale their designs.",
    "evaluation": 1
  },
  {
    "correct_answer": "Mathematics and origami intersect to develop new geometric concepts.",
    "retrieved_context": "advanced origami models explore new possibilities in field. advanced origami models explore possibilities in field. advanced origami models explore possibilities in field of robotics. new possibilities is in field of robotics. advanced origami models explore possibilities. advanced origami models explore new possibilities. advanced origami models explore new possibilities in field of robotics. origami models explore possibilities in field. origami models explore new possibilities. origami models explore new possibilities in field. origami models explore possibilities. new possibilities is in field of robotics. origami models explore possibilities in field of robotics. origami models explore new possibilities in field of robotics. origami mathematics of is In conclusion field. origami involves transformation of sheet of paper. origami involves transformation of sheet of paper into intricate structures. origami involves application of principles. origami involves transformation into structures. origami involves transformation of sheet. origami involves transformation of sheet of paper into intricate three dimensional structures. origami involves transformation of flat sheet into intricate structures. origami involves transformation into intricate structures. origami mathematics of is fascinating field. origami involves transformation of flat sheet of paper into three dimensional structures. origami involves transformation. origami involves transformation of flat sheet of paper into intricate structures. origami involves transformation of flat sheet of paper. origami mathematics of is In conclusion fascinating field. origami involves application In geometry. origami involves transformation At its core. origami involves transformation of flat sheet into intricate three dimensional structures. origami involves transformation of flat sheet into structures. origami involves transformation of sheet of paper into structures. origami involves transformation into three dimensional structures. origami involves transformation of sheet of paper into three dimensional structures. origami involves transformation of sheet into structures. origami involves transformation into intricate three dimensional structures. origami involves transformation of sheet into intricate three dimensional structures. origami mathematics of is field. origami involves transformation of flat sheet of paper into intricate three dimensional structures. origami also involves application of mathematical principles. origami involves transformation of sheet into three dimensional structures. origami involves application. origami involves transformation of flat sheet into three dimensional structures. origami involves transformation of sheet into intricate structures. fascinating field is In conclusion. origami involves transformation of flat sheet of paper into structures. origami involves transformation of flat sheet. Origami art of paper folding.",
    "evaluation": 0
  },
  {
    "correct_answer": "Origami transforms a flat sheet of paper into intricate 3D structures through folds.",
    "retrieved_context": "principles develop innovative structures. simple paper folding techniques as actually involve complex mathematical principles. simple paper folding techniques as actually involve complex principles. principles simple techniques theories. complex mathematical principles simple techniques theories. complex principles techniques theories. principles develop structures. mathematical principles techniques theories. simple paper folding techniques involve principles. simple paper folding techniques as actually involve mathematical principles. principles develop innovative structures. paper folding techniques as actually involve mathematical principles. paper folding techniques as actually involve complex mathematical principles. principles simple techniques theories. paper folding techniques actually involve complex principles. principles develop structures. complex principles techniques theories. complex mathematical principles simple techniques theories. mathematical principles techniques theories. paper folding techniques actually involve principles.",
    "evaluation": 0
  },
  {
    "correct_answer": "Each fold in origami involves precise manipulation of paper's edges, angles, and vertices.",
    "retrieved_context": "principles develop innovative structures. simple paper folding techniques as actually involve complex mathematical principles. simple paper folding techniques as actually involve complex principles. principles simple techniques theories. complex mathematical principles simple techniques theories. complex principles techniques theories. principles develop structures. mathematical principles techniques theories. simple paper folding techniques involve principles. simple paper folding techniques as actually involve mathematical principles. principles develop innovative structures. paper folding techniques as actually involve mathematical principles. paper folding techniques as actually involve complex mathematical principles. principles simple techniques theories. paper folding techniques actually involve complex principles. principles develop structures. complex principles techniques theories. complex mathematical principles simple techniques theories. mathematical principles techniques theories. paper folding techniques actually involve principles. advanced origami models explore new possibilities in field. advanced origami models explore possibilities in field. advanced origami models explore possibilities in field of robotics. new possibilities is in field of robotics. advanced origami models explore possibilities. advanced origami models explore new possibilities. advanced origami models explore new possibilities in field of robotics. origami models explore possibilities in field. origami models explore new possibilities. origami models explore new possibilities in field. origami models explore possibilities. new possibilities is in field of robotics. origami models explore possibilities in field of robotics. origami models explore new possibilities in field of robotics.",
    "evaluation": 0
  },
  {
    "correct_answer": "Mathematical principles guiding origami include symmetry, proportion, and geometry.",
    "retrieved_context": "origami models explore possibilities in field. origami models explore new possibilities. origami models explore new possibilities in field. origami models explore possibilities. new possibilities is in field of robotics. origami models explore possibilities in field of robotics. origami models explore new possibilities in field of robotics. advanced origami models explore new possibilities in field. advanced origami models explore possibilities in field. advanced origami models explore possibilities in field of robotics. new possibilities is in field of robotics. advanced origami models explore possibilities. advanced origami models explore new possibilities. advanced origami models explore new possibilities in field of robotics. origami mathematics of is In conclusion field. origami involves transformation of sheet of paper. origami involves transformation of sheet of paper into intricate structures. origami involves application of principles. origami involves transformation into structures. origami involves transformation of sheet. origami involves transformation of sheet of paper into intricate three dimensional structures. origami involves transformation of flat sheet into intricate structures. origami involves transformation into intricate structures. origami mathematics of is fascinating field. origami involves transformation of flat sheet of paper into three dimensional structures. origami involves transformation. origami involves transformation of flat sheet of paper into intricate structures. origami involves transformation of flat sheet of paper. origami mathematics of is In conclusion fascinating field. origami involves application In geometry. origami involves transformation At its core. origami involves transformation of flat sheet into intricate three dimensional structures. origami involves transformation of flat sheet into structures. origami involves transformation of sheet of paper into structures. origami involves transformation into three dimensional structures. origami involves transformation of sheet of paper into three dimensional structures. origami involves transformation of sheet into structures. origami involves transformation into intricate three dimensional structures. origami involves transformation of sheet into intricate three dimensional structures. origami mathematics of is field. origami involves transformation of flat sheet of paper into intricate three dimensional structures. origami also involves application of mathematical principles. origami involves transformation of sheet into three dimensional structures. origami involves application. origami involves transformation of flat sheet into three dimensional structures. origami involves transformation of sheet into intricate structures. fascinating field is In conclusion. origami involves transformation of flat sheet of paper into structures. origami involves transformation of flat sheet. Origami art of paper folding.",
    "evaluation": 0
  },
  {
    "correct_answer": "Geometry is a fundamental mathematical concept in origami.",
    "retrieved_context": "origami models explore possibilities in field. origami models explore new possibilities. origami models explore new possibilities in field. origami models explore possibilities. new possibilities is in field of robotics. origami models explore possibilities in field of robotics. origami models explore new possibilities in field of robotics. advanced origami models explore new possibilities in field. advanced origami models explore possibilities in field. advanced origami models explore possibilities in field of robotics. new possibilities is in field of robotics. advanced origami models explore possibilities. advanced origami models explore new possibilities. advanced origami models explore new possibilities in field of robotics. origami mathematics of is In conclusion field. origami involves transformation of sheet of paper. origami involves transformation of sheet of paper into intricate structures. origami involves application of principles. origami involves transformation into structures. origami involves transformation of sheet. origami involves transformation of sheet of paper into intricate three dimensional structures. origami involves transformation of flat sheet into intricate structures. origami involves transformation into intricate structures. origami mathematics of is fascinating field. origami involves transformation of flat sheet of paper into three dimensional structures. origami involves transformation. origami involves transformation of flat sheet of paper into intricate structures. origami involves transformation of flat sheet of paper. origami mathematics of is In conclusion fascinating field. origami involves application In geometry. origami involves transformation At its core. origami involves transformation of flat sheet into intricate three dimensional structures. origami involves transformation of flat sheet into structures. origami involves transformation of sheet of paper into structures. origami involves transformation into three dimensional structures. origami involves transformation of sheet of paper into three dimensional structures. origami involves transformation of sheet into structures. origami involves transformation into intricate three dimensional structures. origami involves transformation of sheet into intricate three dimensional structures. origami mathematics of is field. origami involves transformation of flat sheet of paper into intricate three dimensional structures. origami also involves application of mathematical principles. origami involves transformation of sheet into three dimensional structures. origami involves application. origami involves transformation of flat sheet into three dimensional structures. origami involves transformation of sheet into intricate structures. fascinating field is In conclusion. origami involves transformation of flat sheet of paper into structures. origami involves transformation of flat sheet.",
    "evaluation": 0
  },
  {
    "correct_answer": "Euclidean geometry is applied in origami to calculate angles and lengths of folds.",
    "retrieved_context": "advanced origami models explore new possibilities in field. advanced origami models explore possibilities in field. advanced origami models explore possibilities in field of robotics. new possibilities is in field of robotics. advanced origami models explore possibilities. advanced origami models explore new possibilities. advanced origami models explore new possibilities in field of robotics. origami models explore possibilities in field. origami models explore new possibilities. origami models explore new possibilities in field. origami models explore possibilities. new possibilities is in field of robotics. origami models explore possibilities in field of robotics. origami models explore new possibilities in field of robotics. principles develop innovative structures. simple paper folding techniques as actually involve complex mathematical principles. simple paper folding techniques as actually involve complex principles. principles simple techniques theories. complex mathematical principles simple techniques theories. complex principles techniques theories. principles develop structures. mathematical principles techniques theories. simple paper folding techniques involve principles. simple paper folding techniques as actually involve mathematical principles. origami mathematics of is In conclusion field. origami involves transformation of sheet of paper. origami involves transformation of sheet of paper into intricate structures. origami involves application of principles. origami involves transformation into structures. origami involves transformation of sheet. origami involves transformation of sheet of paper into intricate three dimensional structures. origami involves transformation of flat sheet into intricate structures. origami involves transformation into intricate structures. origami mathematics of is fascinating field. origami involves transformation of flat sheet of paper into three dimensional structures. origami involves transformation. origami involves transformation of flat sheet of paper into intricate structures. origami involves transformation of flat sheet of paper. origami mathematics of is In conclusion fascinating field. origami involves application In geometry. origami involves transformation At its core. origami involves transformation of flat sheet into intricate three dimensional structures. origami involves transformation of flat sheet into structures. origami involves transformation of sheet of paper into structures. origami involves transformation into three dimensional structures. origami involves transformation of sheet of paper into three dimensional structures. origami involves transformation of sheet into structures. origami involves transformation into intricate three dimensional structures. origami involves transformation of sheet into intricate three dimensional structures. origami mathematics of is field. origami involves transformation of flat sheet of paper into intricate three dimensional structures. origami also involves application of mathematical principles. origami involves transformation of sheet into three dimensional structures. origami involves application. origami involves transformation of flat sheet into three dimensional structures. origami involves transformation of sheet into intricate structures. fascinating field is In conclusion. origami involves transformation of flat sheet of paper into structures. origami involves transformation of flat sheet.",
    "evaluation": 0
  },
  {
    "correct_answer": "Symmetry is a key mathematical concept in origami for creating visually appealing designs.",
    "retrieved_context": "origami models explore possibilities in field. origami models explore new possibilities. origami models explore new possibilities in field. origami models explore possibilities. new possibilities is in field of robotics. origami models explore possibilities in field of robotics. origami models explore new possibilities in field of robotics. advanced origami models explore new possibilities in field. advanced origami models explore possibilities in field. advanced origami models explore possibilities in field of robotics. new possibilities is in field of robotics. advanced origami models explore possibilities. advanced origami models explore new possibilities. advanced origami models explore new possibilities in field of robotics. Symmetry refers to balance. Symmetry refers to balance of shapes in design. Symmetry refers to balance of shapes. Symmetry refers to balance in design. balance is in design.",
    "evaluation": 0
  },
  {
    "correct_answer": "Symmetrical folds and repetitions enhance the beauty and stability of origami models.",
    "retrieved_context": "origami models explore possibilities in field. origami models explore new possibilities. origami models explore new possibilities in field. origami models explore possibilities. new possibilities is in field of robotics. origami models explore possibilities in field of robotics. origami models explore new possibilities in field of robotics. advanced origami models explore new possibilities in field. advanced origami models explore possibilities in field. advanced origami models explore possibilities in field of robotics. new possibilities is in field of robotics. advanced origami models explore possibilities. advanced origami models explore new possibilities. advanced origami models explore new possibilities in field of robotics. origami mathematics of is In conclusion field. origami involves transformation of sheet of paper. origami involves transformation of sheet of paper into intricate structures. origami involves application of principles. origami involves transformation into structures. origami involves transformation of sheet. origami involves transformation of sheet of paper into intricate three dimensional structures. origami involves transformation of flat sheet into intricate structures. origami involves transformation into intricate structures. origami mathematics of is fascinating field. origami involves transformation of flat sheet of paper into three dimensional structures. origami involves transformation. origami involves transformation of flat sheet of paper into intricate structures. origami involves transformation of flat sheet of paper. origami mathematics of is In conclusion fascinating field. origami involves application In geometry. origami involves transformation At its core. origami involves transformation of flat sheet into intricate three dimensional structures. origami involves transformation of flat sheet into structures. origami involves transformation of sheet of paper into structures. origami involves transformation into three dimensional structures. origami involves transformation of sheet of paper into three dimensional structures. origami involves transformation of sheet into structures. origami involves transformation into intricate three dimensional structures. origami involves transformation of sheet into intricate three dimensional structures. origami mathematics of is field. origami involves transformation of flat sheet of paper into intricate three dimensional structures. origami also involves application of mathematical principles. origami involves transformation of sheet into three dimensional structures. origami involves application. origami involves transformation of flat sheet into three dimensional structures. origami involves transformation of sheet into intricate structures. fascinating field is In conclusion. origami involves transformation of flat sheet of paper into structures. origami involves transformation of flat sheet.",
    "evaluation": 0
  },
  {
    "correct_answer": "Proportion and ratio are important mathematical principles in origami design.",
    "retrieved_context": "advanced origami models explore new possibilities in field. advanced origami models explore possibilities in field. advanced origami models explore possibilities in field of robotics. new possibilities is in field of robotics. advanced origami models explore possibilities. advanced origami models explore new possibilities. advanced origami models explore new possibilities in field of robotics. origami models explore possibilities in field. origami models explore new possibilities. origami models explore new possibilities in field. origami models explore possibilities. new possibilities is in field of robotics. origami models explore possibilities in field of robotics. origami models explore new possibilities in field of robotics. origami mathematics of is In conclusion field. origami involves transformation of sheet of paper. origami involves transformation of sheet of paper into intricate structures. origami involves application of principles. origami involves transformation into structures. origami involves transformation of sheet. origami involves transformation of sheet of paper into intricate three dimensional structures. origami involves transformation of flat sheet into intricate structures. origami involves transformation into intricate structures. origami mathematics of is fascinating field. origami involves transformation of flat sheet of paper into three dimensional structures. origami involves transformation. origami involves transformation of flat sheet of paper into intricate structures. origami involves transformation of flat sheet of paper. origami mathematics of is In conclusion fascinating field. origami involves application In geometry. origami involves transformation At its core. origami involves transformation of flat sheet into intricate three dimensional structures. origami involves transformation of flat sheet into structures. origami involves transformation of sheet of paper into structures. origami involves transformation into three dimensional structures. origami involves transformation of sheet of paper into three dimensional structures. origami involves transformation of sheet into structures. origami involves transformation into intricate three dimensional structures. origami involves transformation of sheet into intricate three dimensional structures. origami mathematics of is field. origami involves transformation of flat sheet of paper into intricate three dimensional structures. origami also involves application of mathematical principles. origami involves transformation of sheet into three dimensional structures. origami involves application. origami involves transformation of flat sheet into three dimensional structures. origami involves transformation of sheet into intricate structures. fascinating field is In conclusion. origami involves transformation of flat sheet of paper into structures. origami involves transformation of flat sheet. Origami art of paper folding. principles develop innovative structures. simple paper folding techniques as actually involve complex mathematical principles. simple paper folding techniques as actually involve complex principles. principles simple techniques theories. complex mathematical principles simple techniques theories. complex principles techniques theories. principles develop structures. mathematical principles techniques theories. simple paper folding techniques involve principles. simple paper folding techniques as actually involve mathematical principles.",
    "evaluation": 0
  },
  {
    "correct_answer": "Origami principles have applications in engineering, architecture, and material science.",
    "retrieved_context": "advanced origami models explore new possibilities in field. advanced origami models explore possibilities in field. advanced origami models explore possibilities in field of robotics. new possibilities is in field of robotics. advanced origami models explore possibilities. advanced origami models explore new possibilities. advanced origami models explore new possibilities in field of robotics. origami models explore possibilities in field. origami models explore new possibilities. origami models explore new possibilities in field. origami models explore possibilities. new possibilities is in field of robotics. origami models explore possibilities in field of robotics. origami models explore new possibilities in field of robotics. origami mathematics of is In conclusion field. origami involves transformation of sheet of paper. origami involves transformation of sheet of paper into intricate structures. origami involves application of principles. origami involves transformation into structures. origami involves transformation of sheet. origami involves transformation of sheet of paper into intricate three dimensional structures. origami involves transformation of flat sheet into intricate structures. origami involves transformation into intricate structures. origami mathematics of is fascinating field. origami involves transformation of flat sheet of paper into three dimensional structures. origami involves transformation. origami involves transformation of flat sheet of paper into intricate structures. origami involves transformation of flat sheet of paper. origami mathematics of is In conclusion fascinating field. origami involves application In geometry. origami involves transformation At its core. origami involves transformation of flat sheet into intricate three dimensional structures. origami involves transformation of flat sheet into structures. origami involves transformation of sheet of paper into structures. origami involves transformation into three dimensional structures. origami involves transformation of sheet of paper into three dimensional structures. origami involves transformation of sheet into structures. origami involves transformation into intricate three dimensional structures. origami involves transformation of sheet into intricate three dimensional structures. origami mathematics of is field. origami involves transformation of flat sheet of paper into intricate three dimensional structures. origami also involves application of mathematical principles. origami involves transformation of sheet into three dimensional structures. origami involves application. origami involves transformation of flat sheet into three dimensional structures. origami involves transformation of sheet into intricate structures. fascinating field is In conclusion. origami involves transformation of flat sheet of paper into structures. origami involves transformation of flat sheet. Origami art of paper folding. principles develop innovative structures. paper folding techniques as actually involve mathematical principles. paper folding techniques as actually involve complex mathematical principles. principles simple techniques theories. paper folding techniques actually involve complex principles. principles develop structures. complex principles techniques theories. complex mathematical principles simple techniques theories. mathematical principles techniques theories. paper folding techniques actually involve principles. origami artists can create appealing models. origami artists maintaining integrity. origami artists can create visually appealing models. origami artists can create models By symmetrical folds. origami artists maintaining integrity of structure. origami artists can create models By incorporating folds. origami artists maintaining integrity of original structure. origami artists can create models By incorporating symmetrical folds. origami artists can create models. origami artists can create models By folds. origami artists can scale their designs.",
    "evaluation": 0
  },
  {
    "correct_answer": "Origami-inspired principles have been used to develop innovative structures like solar panels.",
    "retrieved_context": "advanced origami models explore new possibilities in field. advanced origami models explore possibilities in field. advanced origami models explore possibilities in field of robotics. new possibilities is in field of robotics. advanced origami models explore possibilities. advanced origami models explore new possibilities. advanced origami models explore new possibilities in field of robotics. origami models explore possibilities in field. origami models explore new possibilities. origami models explore new possibilities in field. origami models explore possibilities. new possibilities is in field of robotics. origami models explore possibilities in field of robotics. origami models explore new possibilities in field of robotics. origami mathematics of is In conclusion field. origami involves transformation of sheet of paper. origami involves transformation of sheet of paper into intricate structures. origami involves application of principles. origami involves transformation into structures. origami involves transformation of sheet. origami involves transformation of sheet of paper into intricate three dimensional structures. origami involves transformation of flat sheet into intricate structures. origami involves transformation into intricate structures. origami mathematics of is fascinating field. origami involves transformation of flat sheet of paper into three dimensional structures. origami involves transformation. origami involves transformation of flat sheet of paper into intricate structures. origami involves transformation of flat sheet of paper. origami mathematics of is In conclusion fascinating field. origami involves application In geometry. origami involves transformation At its core. origami involves transformation of flat sheet into intricate three dimensional structures. origami involves transformation of flat sheet into structures. origami involves transformation of sheet of paper into structures. origami involves transformation into three dimensional structures. origami involves transformation of sheet of paper into three dimensional structures. origami involves transformation of sheet into structures. origami involves transformation into intricate three dimensional structures. origami involves transformation of sheet into intricate three dimensional structures. origami mathematics of is field. origami involves transformation of flat sheet of paper into intricate three dimensional structures. origami also involves application of mathematical principles. origami involves transformation of sheet into three dimensional structures. origami involves application. origami involves transformation of flat sheet into three dimensional structures. origami involves transformation of sheet into intricate structures. fascinating field is In conclusion. origami involves transformation of flat sheet of paper into structures. origami involves transformation of flat sheet. Origami art of paper folding. principles develop innovative structures. paper folding techniques as actually involve mathematical principles. paper folding techniques as actually involve complex mathematical principles. principles simple techniques theories. paper folding techniques actually involve complex principles. principles develop structures. complex principles techniques theories. complex mathematical principles simple techniques theories. mathematical principles techniques theories. paper folding techniques actually involve principles. principles develop innovative structures. simple paper folding techniques as actually involve complex mathematical principles. simple paper folding techniques as actually involve complex principles. principles simple techniques theories. complex mathematical principles simple techniques theories. complex principles techniques theories. principles develop structures. mathematical principles techniques theories. simple paper folding techniques involve principles. simple paper folding techniques as actually involve mathematical principles.",
    "evaluation": 0
  },
  {
    "correct_answer": "Computational origami involves developing algorithms to simulate folding patterns.",
    "retrieved_context": "advanced origami models explore new possibilities in field. advanced origami models explore possibilities in field. advanced origami models explore possibilities in field of robotics. new possibilities is in field of robotics. advanced origami models explore possibilities. advanced origami models explore new possibilities. advanced origami models explore new possibilities in field of robotics. origami models explore possibilities in field. origami models explore new possibilities. origami models explore new possibilities in field. origami models explore possibilities. new possibilities is in field of robotics. origami models explore possibilities in field of robotics. origami models explore new possibilities in field of robotics. principles develop innovative structures. simple paper folding techniques as actually involve complex mathematical principles. simple paper folding techniques as actually involve complex principles. principles simple techniques theories. complex mathematical principles simple techniques theories. complex principles techniques theories. principles develop structures. mathematical principles techniques theories. simple paper folding techniques involve principles. simple paper folding techniques as actually involve mathematical principles. principles develop innovative structures. paper folding techniques as actually involve mathematical principles. paper folding techniques as actually involve complex mathematical principles. principles simple techniques theories. paper folding techniques actually involve complex principles. principles develop structures. complex principles techniques theories. complex mathematical principles simple techniques theories. mathematical principles techniques theories. paper folding techniques actually involve principles.",
    "evaluation": 0
  },
  {
    "correct_answer": "Mathematics of origami has contributed to advancements in robotics and artificial intelligence.",
    "retrieved_context": "advanced origami models explore new possibilities in field. advanced origami models explore possibilities in field. advanced origami models explore possibilities in field of robotics. new possibilities is in field of robotics. advanced origami models explore possibilities. advanced origami models explore new possibilities. advanced origami models explore new possibilities in field of robotics. origami models explore possibilities in field. origami models explore new possibilities. origami models explore new possibilities in field. origami models explore possibilities. new possibilities is in field of robotics. origami models explore possibilities in field of robotics. origami models explore new possibilities in field of robotics. origami mathematics of is In conclusion field. origami involves transformation of sheet of paper. origami involves transformation of sheet of paper into intricate structures. origami involves application of principles. origami involves transformation into structures. origami involves transformation of sheet. origami involves transformation of sheet of paper into intricate three dimensional structures. origami involves transformation of flat sheet into intricate structures. origami involves transformation into intricate structures. origami mathematics of is fascinating field. origami involves transformation of flat sheet of paper into three dimensional structures. origami involves transformation. origami involves transformation of flat sheet of paper into intricate structures. origami involves transformation of flat sheet of paper. origami mathematics of is In conclusion fascinating field. origami involves application In geometry. origami involves transformation At its core. origami involves transformation of flat sheet into intricate three dimensional structures. origami involves transformation of flat sheet into structures. origami involves transformation of sheet of paper into structures. origami involves transformation into three dimensional structures. origami involves transformation of sheet of paper into three dimensional structures. origami involves transformation of sheet into structures. origami involves transformation into intricate three dimensional structures. origami involves transformation of sheet into intricate three dimensional structures. origami mathematics of is field. origami involves transformation of flat sheet of paper into intricate three dimensional structures. origami also involves application of mathematical principles. origami involves transformation of sheet into three dimensional structures. origami involves application. origami involves transformation of flat sheet into three dimensional structures. origami involves transformation of sheet into intricate structures. fascinating field is In conclusion. origami involves transformation of flat sheet of paper into structures. origami involves transformation of flat sheet. Origami art of paper folding. origami artists can create appealing models. origami artists maintaining integrity. origami artists can create visually appealing models. origami artists can create models By symmetrical folds. origami artists maintaining integrity of structure. origami artists can create models By incorporating folds. origami artists maintaining integrity of original structure. origami artists can create models By incorporating symmetrical folds. origami artists can create models. origami artists can create models By folds. origami artists can scale their designs. principles develop innovative structures. paper folding techniques as actually involve mathematical principles. paper folding techniques as actually involve complex mathematical principles. principles simple techniques theories. paper folding techniques actually involve complex principles. principles develop structures. complex principles techniques theories. complex mathematical principles simple techniques theories. mathematical principles techniques theories. paper folding techniques actually involve principles.",
    "evaluation": 0
  },
  {
    "accuracy": "6.67%"
  }
]